{
  "C:\\Program Files\\Java\\jre1.8.0_101\\lib\\rt.jar": {
    "coordinate": "jre:jre:zip:call:1.0.0",
    "location": "C:\\Program Files\\Java\\jre1.8.0_101\\lib\\rt.jar",
    "status": "RESOLVED"
  },
  "C:\\ssa4week\\day3\\sampleWorkspace\\dayThreeJavaWorkspace\\src": {
    "location": "C:\\ssa4week\\day3\\sampleWorkspace\\dayThreeJavaWorkspace\\src",
    "status": "UNRESOLVED",
    "error": "No class path info available for \u0027C:\\ssa4week\\day3\\sampleWorkspace\\dayThreeJavaWorkspace\\src\u0027. Skipped."
  }
}